subflowchart_step/__init__.py
subflowchart_step/_version.py
subflowchart_step/subflowchart.py
subflowchart_step/subflowchart_step.py
subflowchart_step/tk_subflowchart.py
subflowchart_step/data/properties.csv
subflowchart_step/data/references.bib
subflowchart_step-2025.3.4.dist-info/AUTHORS.rst
subflowchart_step-2025.3.4.dist-info/LICENSE
subflowchart_step-2025.3.4.dist-info/METADATA
subflowchart_step-2025.3.4.dist-info/WHEEL
subflowchart_step-2025.3.4.dist-info/entry_points.txt
subflowchart_step-2025.3.4.dist-info/top_level.txt
subflowchart_step-2025.3.4.dist-info/zip-safe
subflowchart_step-2025.3.4.dist-info/RECORD
